setup1.py
VoiceBot/Bot.py
VoiceBot/BotServer.py
VoiceBot/CallCenter.py
VoiceBot/Esl_AsrDemo.py
VoiceBot/InboundDemo.py
VoiceBot/SampleBot.py
VoiceBot/__init__.py
VoiceBot/AutoCall/AutoDialer.py
VoiceBot/AutoCall/Dialer.py
VoiceBot/AutoCall/__init__.py
VoiceBot/MyDialog/__init__.py
VoiceBot/MyDialog/d_payback.py
ai_bot/__init__.py
ai_bot.egg-info/PKG-INFO
ai_bot.egg-info/SOURCES.txt
ai_bot.egg-info/dependency_links.txt
ai_bot.egg-info/top_level.txt
callcenter/__init__.py