Metadata-Version: 1.0
Name: ai-bot
Version: 0.0.1
Summary: 18-ai_bot0.1.0
Home-page: https://github.com/MaPing01/pipProject
Author: MaPing01
Author-email: pingpingma001@163.com
License: MIT Licence
Keywords: pip,BotServer,Callcenter,VoiceBot,ai_bot,callcenter
Platform: any
